LICENSE.txt
MANIFEST.in
README.md
requirements.txt
setup.cfg
setup.py
htools/__init__.py
htools/autodebug.py
htools/cli.py
htools/config.py
htools/core.py
htools/magics.py
htools/meta.py
htools/pd_tools.py
htools/structures.py
htools.egg-info/PKG-INFO
htools.egg-info/SOURCES.txt
htools.egg-info/dependency_links.txt
htools.egg-info/entry_points.txt
htools.egg-info/not-zip-safe
htools.egg-info/requires.txt
htools.egg-info/top_level.txt