Metadata-Version: 2.1
Name: htools
Version: 7.5.0
Summary: Harrison's custom functions.
Author: Harrison Mamin
License: UNKNOWN
Platform: UNKNOWN
Provides-Extra: fuzzy
Provides-Extra: speedup
License-File: LICENSE.txt
